subscriptions/__init__.py
subscriptions/admin.py
subscriptions/apps.py
subscriptions/fsm_hooks.py
subscriptions/migrations/0001_init.py
subscriptions/migrations/0002_statetext.py
subscriptions/migrations/0003_stateorder.py
subscriptions/migrations/__init__.py
subscriptions/models.py
subscriptions/signals.py
subscriptions/states.py
subscriptions/tasks.py
django_subscriptions-2.1.0.dist-info/LICENSE
django_subscriptions-2.1.0.dist-info/WHEEL
django_subscriptions-2.1.0.dist-info/METADATA
django_subscriptions-2.1.0.dist-info/RECORD
