Metadata-Version: 2.1
Name: django-subscriptions
Version: 2.1.0
Summary: A django package for managing subscription states
Home-page: http://github.com/kogan/
License: BSD-3-Clause
Keywords: subscriptions,django
Author: Josh Smeaton
Author-email: josh.smeaton@gmail.com
Requires-Python: >=3.6
Classifier: Framework :: Django
Classifier: Framework :: Django :: 2.2
Classifier: Intended Audience :: Developers
Classifier: License :: OSI Approved :: BSD License
Classifier: Natural Language :: English
Classifier: Programming Language :: Python
Classifier: Programming Language :: Python :: 3
Classifier: Programming Language :: Python :: 3.6
Classifier: Programming Language :: Python :: 3.7
Classifier: Programming Language :: Python :: 3.8
Requires-Dist: django-fsm (>=2.6)
Requires-Dist: django-fsm-log (>=1.6)
Project-URL: Documentation, http://github.com/kogan/django-subscriptions/
Project-URL: Repository, http://github.com/kogan/django-subscriptions/
